{"trial_id": "07", "hyperparameters": {"space": [{"class_name": "Int", "config": {"name": "lstm_units1", "default": null, "conditions": [], "min_value": 50, "max_value": 200, "step": 50, "sampling": "linear"}}, {"class_name": "Float", "config": {"name": "dropout1", "default": 0.1, "conditions": [], "min_value": 0.1, "max_value": 0.5, "step": 0.1, "sampling": "linear"}}, {"class_name": "Int", "config": {"name": "lstm_units2", "default": null, "conditions": [], "min_value": 50, "max_value": 150, "step": 50, "sampling": "linear"}}, {"class_name": "Float", "config": {"name": "dropout2", "default": 0.1, "conditions": [], "min_value": 0.1, "max_value": 0.5, "step": 0.1, "sampling": "linear"}}, {"class_name": "Choice", "config": {"name": "optimizer", "default": "adam", "conditions": [], "values": ["adam", "rmsprop"], "ordered": false}}, {"class_name": "Choice", "config": {"name": "learning_rate", "default": 0.01, "conditions": [], "values": [0.01, 0.001, 0.0001], "ordered": true}}], "values": {"lstm_units1": 150, "dropout1": 0.5, "lstm_units2": 100, "dropout2": 0.4, "optimizer": "rmsprop", "learning_rate": 0.0001}}, "metrics": {"metrics": {"loss": {"direction": "min", "observations": [{"value": [3621.234130859375], "step": 16}]}, "mae": {"direction": "min", "observations": [{"value": [49.03136444091797], "step": 16}]}, "val_loss": {"direction": "min", "observations": [{"value": [4463.3193359375], "step": 16}]}, "val_mae": {"direction": "min", "observations": [{"value": [53.94024658203125], "step": 16}]}}}, "score": 4463.3193359375, "best_step": 16, "status": "COMPLETED", "message": null}